braincore/__init__.py
braincore/_common.py
braincore/_module.py
braincore/_module_test.py
braincore/_state.py
braincore/_state_test.py
braincore/environ.py
braincore/mixin.py
braincore/mixin_test.py
braincore/random.py
braincore/random_test.py
braincore/share.py
braincore/surrogate.py
braincore/typing.py
braincore/util.py
braincore/_projection/__init__.py
braincore/_projection/_align_post.py
braincore/_projection/_align_pre.py
braincore/_projection/_delta.py
braincore/_projection/_utils.py
braincore/_projection/_vanilla.py
braincore/integrate/__init__.py
braincore/integrate/_joint_eq.py
braincore/integrate/_ode.py
braincore/integrate/_quadrature.py
braincore/math/__init__.py
braincore/math/_einops.py
braincore/math/_einops_parsing.py
braincore/math/_einops_parsing_test.py
braincore/math/_einops_test.py
braincore/math/_misc.py
braincore/math/_misc_test.py
braincore/transform/__init__.py
braincore/transform/_autograd.py
braincore/transform/_autograd_test.py
braincore/transform/_control.py
braincore/transform/_controls_test.py
braincore/transform/_jit.py
braincore/transform/_jit_error.py
braincore/transform/_jit_test.py
braincore/transform/_make_jaxpr.py
braincore/transform/_make_jaxpr_test.py
braincore/transform/_progress_bar.py
braincore/units/__init__.py
braincore-0.0.3.dist-info/LICENSE
braincore-0.0.3.dist-info/METADATA
braincore-0.0.3.dist-info/WHEEL
braincore-0.0.3.dist-info/top_level.txt
braincore-0.0.3.dist-info/RECORD
