Metadata-Version: 2.1
Name: braincore
Version: 0.0.3
Summary: The Core System for General-purpose Brain Dynamics Programming Framework.
Home-page: https://github.com/brainpy/braincore
Author: BrainPy Team
Author-email: BrainPy Team <chao.brain@qq.com>
License: Apache-2.0 license
Project-URL: homepage, http://github.com/brainpy
Project-URL: repository, http://github.com/brainpy/braincore
Keywords: brainpy,brain simulation,brain-inspired computing
Classifier: Natural Language :: English
Classifier: Operating System :: OS Independent
Classifier: Development Status :: 4 - Beta
Classifier: Intended Audience :: Developers
Classifier: Intended Audience :: Science/Research
Classifier: Programming Language :: Python :: 3
Classifier: Programming Language :: Python :: 3.9
Classifier: Programming Language :: Python :: 3.10
Classifier: Programming Language :: Python :: 3.11
Classifier: Programming Language :: Python :: 3.12
Classifier: License :: OSI Approved :: Apache Software License
Classifier: Programming Language :: Python
Classifier: Topic :: Scientific/Engineering :: Bio-Informatics
Classifier: Topic :: Scientific/Engineering :: Mathematics
Classifier: Topic :: Scientific/Engineering :: Artificial Intelligence
Classifier: Topic :: Software Development :: Libraries
Requires-Python: >=3.9
License-File: LICENSE
Requires-Dist: jax
Requires-Dist: jaxlib
Requires-Dist: numpy
Provides-Extra: cpu
Requires-Dist: jaxlib ; extra == 'cpu'
Requires-Dist: brainpylib ; extra == 'cpu'
Provides-Extra: cpu_mini
Requires-Dist: jaxlib ; extra == 'cpu_mini'
Provides-Extra: cuda11
Requires-Dist: jaxlib[cuda11_pip] ; extra == 'cuda11'
Requires-Dist: brainpylib ; extra == 'cuda11'
Provides-Extra: cuda11_mini
Requires-Dist: jaxlib[cuda11_pip] ; extra == 'cuda11_mini'
Provides-Extra: cuda12
Requires-Dist: jaxlib[cuda12_pip] ; extra == 'cuda12'
Requires-Dist: brainpylib ; extra == 'cuda12'
Provides-Extra: cuda12_mini
Requires-Dist: jaxlib[cuda12_pip] ; extra == 'cuda12_mini'
Provides-Extra: testing
Requires-Dist: pytest ; extra == 'testing'
Provides-Extra: tpu
Requires-Dist: jaxlib[tpu] ; extra == 'tpu'
